tb/i2c_task.v
// ==== SLAVE HANDLE WRITE (Master writes to PCF8575) ====
task pcf8575_slave_handle_write();
    integer rdata;
    begin
        $display("=====pcf8575_slave_handle_write=====");
        slave_wait_start();

        slave_receive_byte(rdata); // address + W

        if (rdata == {I2C_PCF8575_SLAVE_ADDR, 1'b0}) begin
            // Correct address + WRITE
            $display("[PCF8575] Address matched: 7'h%h, WRITE operation",rdata[7:1]);
            slave_send_ack(1);

            slave_receive_byte(rdata); // MSB
            slave_send_ack(1);

            slave_receive_byte(rdata); // LSB
            slave_send_ack(0);
        end
        else if (rdata[7:1] == I2C_PCF8575_SLAVE_ADDR) begin
            // Address correct but R/W bit wrong
            $display("[PCF8575] Address matched but R/W bit incorrect (Expected WRITE)");
            slave_send_ack(0); // optional NACK
        end
        else begin
            // Address incorrect
            $display("[PCF8575] Address mismatch (Wrong slave address)");
            slave_send_ack(0); // optional NACK
        end


        slave_wait_stop();
    end
endtask


// ==== SLAVE HANDLE READ (Master reads from PCF8575) ====
task pcf8575_slave_handle_read(
        input [15:0] data
    );
    integer rdata;
    integer master_ack;
    begin
        $display("=====pcf8575_slave_handle_read=====");
        master_ack = 0;
        slave_wait_start();

        slave_receive_byte(rdata); // address + R
        
        if (rdata == {I2C_PCF8575_SLAVE_ADDR, 1'b1}) begin
            // Correct address + READ
            $display("[PCF8575] Address matched: 7'h%h, READ operation",rdata[7:1]);
            slave_send_ack(1);

            slave_transmit_byte(data[15:8]); // MSB
            slave_check_master_ack(master_ack);

            if (master_ack) begin
                slave_transmit_byte(data[7:0]); // LSB
                slave_check_master_ack(master_ack);
            end
        end
        else if (rdata[7:1] == I2C_PCF8575_SLAVE_ADDR) begin
            // Address correct but R/W bit wrong
            $display("[PCF8575] Address matched but R/W bit incorrect (Expected READ)");
            slave_send_ack(0); // optional: NACK wrong direction
        end
        else begin
            // Address incorrect
            $display("[PCF8575] Address mismatch (Wrong slave address)");
            slave_send_ack(0); // optional
        end


        slave_wait_stop();
    end
endtask


// ==== WAIT START CONDITION ====
task slave_wait_start();
    reg detect;
    begin
        $display("[%0t] [PCF8575] Waiting for START condition", $time);
        detect = 0;
        while (!detect) begin
            @(negedge tb.SDA_bus);
            if (tb.SCL_bus === 1'b1) begin
                $display("[%0t] [PCF8575] START detected", $time);
                detect = 1;
            end
        end
    end
endtask


// ==== WAIT STOP CONDITION ====
task slave_wait_stop();
    reg detect;
    begin
        $display("[%0t] [PCF8575] Waiting for STOP condition", $time);
        detect = 0;
        while (!detect) begin
            @(posedge tb.SDA_bus);
            if (tb.SCL_bus === 1'b1) begin
                $display("[%0t] [PCF8575] STOP detected", $time);
                detect = 1;
            end
        end
    end
endtask


// ==== SLAVE RECEIVE BYTE FROM MASTER ====
task slave_receive_byte(output [7:0] data);
    integer i;
    begin
        tb.sda_drive = 0; // release SDA
        for (i = 8; i > 0; i = i - 1) begin
            @(posedge tb.SCL_bus)
                data[i-1] = tb.SDA_bus;
        end
        $display("[%0t] [PCF8575] Received byte: 0x%02h", $time, data);
    end
endtask


// ==== SLAVE TRANSMIT BYTE TO MASTER ====
task slave_transmit_byte(input [7:0] data);
    integer i;
    begin
        $display("[%0t] [PCF8575] Transmitting byte: 0x%02h", $time, data);
        for (i = 8; i > 0; i = i - 1) begin
            @(negedge tb.SCL_bus)
                tb.sda_drive = ~data[i-1];
        end
    end
endtask


// ==== SLAVE SEND ACK/NACK ====
task slave_send_ack(input ack);
    begin
        @(negedge tb.SCL_bus) tb.sda_drive = ack;
        if (ack)
            $display("[%0t] [PCF8575] Send ACK", $time);
        else
            $display("[%0t] [PCF8575] Send NACK", $time);
        @(negedge tb.SCL_bus) tb.sda_drive = 0; // release SDA
    end
endtask


// ==== SLAVE CHECK MASTER ACK ====
task slave_check_master_ack(output ack);
    begin
        @(negedge tb.SCL_bus) tb.sda_drive = 0;
        @(posedge tb.SCL_bus) ack = tb.sda_drive;

        if (ack)
            $display("[%0t] [PCF8575] Master ACK received", $time);
        else
            $display("[%0t] [PCF8575] Master NACK received", $time);
    end
endtask

src/pcf8575.v
module pcf8575 (
    input wire clk, rst_n,

    input wire [2:0] addr,
    input wire [15:0] wdata,
    output reg [15:0] rdata,

    inout wire SDA_bus,
    output wire SCL_bus,
    input wire int_sig
);

    localparam I2C_PCF8575_FIST_4B_SLAVE_ADDR = 4'b0100;

    reg scl_en, scl_drive;
    assign SCL_bus = (scl_drive)? 1'b0: 1'bz;

    always @(posedge clk , negedge rst_n) begin
        if(!rst_n) scl_drive <= 1'b0;
        else if (scl_en) scl_drive <= ~scl_drive;
        else scl_drive <= 1'b0;
    end

    
    
    reg [7:0] data_shift_out;
    reg sda_fsm_drive;
    assign SDA_bus = (sda_fsm_drive)? 1'b0: 1'bz;
    reg [4:0] data_shift_count;
        
    reg [3:0] state, next_state;

    reg[15:0] wdata_sub_reg, rdata_sub_reg;
    reg write_update;
    // assign write_update = (wdata_sub_reg != rdata_sub_reg);

    localparam
        ST_IDLE        = 4'd0,
        ST_START       = 4'd1,
        ST_SLAVE_ADDR  = 4'd2,
        ST_ADDR_ACK    = 4'd4,
        ST_WRITE_DATA  = 4'd5,
        ST_WRITE_ACK   = 4'd6,
        ST_READ_DATA   = 4'd7,
        ST_READ_ACK    = 4'd8,
        ST_STOP        = 4'd9;


    always @(negedge clk , negedge rst_n) begin
        if(!rst_n)begin
            state <= ST_IDLE;
            wdata_sub_reg <= 16'h0;
            rdata_sub_reg <= 0;
            data_shift_count <= 0;
            scl_en <= 0;
            sda_fsm_drive <= 0;
            write_update = 1'b0;
            rdata <= 0;
        end
        else begin
            case (state)
                ST_IDLE: begin
                    write_update <= (wdata_sub_reg != wdata);
                    // write_update <= 0;
                    sda_fsm_drive <= 0;
                    data_shift_count <= 0;
                    scl_en <= 0;
                    sda_fsm_drive <= 0;

                    if(write_update || !int_sig) begin
                        state <= ST_START;
                    end
                    else begin
                        state <= ST_IDLE;
                    end
                end 

                ST_START: begin
                    sda_fsm_drive <= 1;
                    scl_en <= 1;
                    state <= ST_SLAVE_ADDR;
                    data_shift_count <= 0;
                end

                ST_SLAVE_ADDR:begin
                    sda_fsm_drive <= 0;
                    if(data_shift_count <= 4'd3) sda_fsm_drive <= ~I2C_PCF8575_FIST_4B_SLAVE_ADDR[3'd3-data_shift_count[2:0]];
                    else if(data_shift_count <= 4'd6) sda_fsm_drive <= ~addr[3'd6-data_shift_count[2:0]];
                    else begin
                        if(write_update)        sda_fsm_drive <=  ~(1'b0);
                        else                    sda_fsm_drive <=  ~(1'b1);
                    end

                    if(!scl_drive)begin
                        data_shift_count <= data_shift_count +1'b1;
                    end
                    else data_shift_count <= data_shift_count ;
                    
                    if(data_shift_count <= 4'd7)begin
                        state <= ST_SLAVE_ADDR;
                    end
                    else begin
                        sda_fsm_drive <= 0;
                        state <= ST_ADDR_ACK;
                        // write_shift_start <= 0;
                    end
                end

                ST_ADDR_ACK:begin
                    if (!scl_drive) begin
                        if(SDA_bus) begin
                            state <= ST_STOP;
                        end
                        else begin
                            sda_fsm_drive <= 0;
                            data_shift_count <= 0;
                            if(write_update)  begin
                                state <= ST_WRITE_DATA;
                                wdata_sub_reg <= wdata;
                                data_shift_count <= 5'd17;
                            end
                            else if(!int_sig)    state <= ST_READ_DATA;
                            else state <= ST_STOP;
                            
                        end
                    end
                    else state <= ST_ADDR_ACK;
                end

                ST_WRITE_DATA: begin
                    // Mặc định drive SDA
                    sda_fsm_drive <= 1'b0;
                    // Byte thấp: count 17 -> 10 (bit 7 -> 0)
                    if (data_shift_count <= 5'd17 && data_shift_count >= 5'd10)
                        sda_fsm_drive <= ~wdata_sub_reg[data_shift_count - 5'd10];

                    // Byte cao: count 8 -> 1 (bit 15 -> 8)
                    else if (data_shift_count <= 5'd8 && data_shift_count >= 5'd1)
                        sda_fsm_drive <= ~wdata_sub_reg[data_shift_count + 5'd7];

                    // Truyền dữ liệu khi SCL = 0
                    if (!scl_drive) begin
                        data_shift_count <= data_shift_count - 1'b1;
                    end
                    else data_shift_count <= data_shift_count ;

                    // Hết 1 byte → sang ACK
                    if (data_shift_count == 5'd9 || data_shift_count == 5'd0) begin
                        sda_fsm_drive <= 1'b0; // nhả SDA
                        state <= ST_WRITE_ACK;
                    end
                    else begin
                        state <= ST_WRITE_DATA;
                    end
                end


                ST_WRITE_ACK: begin
                    sda_fsm_drive <= 1'b0; // nhả SDA để slave ACK

                    if (!scl_drive) begin
                        // Sau ACK byte thấp → gửi byte cao
                        if (data_shift_count == 5'd9) begin
                            data_shift_count <= 5'd8;
                            state <= ST_WRITE_DATA;
                        end
                        // Sau ACK byte cao → STOP
                        else if (data_shift_count == 5'd0) begin
                            state <= ST_STOP;
                            scl_en <= 1'b1;
                            sda_fsm_drive <= 1'b0;
                        end
                    end
                    else begin
                        state <= ST_WRITE_ACK;
                    end
                end


                ST_READ_DATA:begin
                    sda_fsm_drive <= 0;
                    if(!scl_drive)begin
                        data_shift_count <= data_shift_count +1'b1;
                        if(data_shift_count < 5'd8)   rdata_sub_reg <= {rdata_sub_reg[15:8],rdata_sub_reg[6:0],SDA_bus};
                        else if(data_shift_count < 5'd17)   rdata_sub_reg <= {rdata_sub_reg[14:8],SDA_bus,rdata_sub_reg[7:0]};
                        else  rdata_sub_reg <= rdata_sub_reg;
                    end
                    else data_shift_count <= data_shift_count ;
                    
                    if(data_shift_count == 5'd8 || data_shift_count == 5'd17)begin
                        if(data_shift_count == 5'd17) rdata <= rdata_sub_reg;
                        state <= ST_READ_ACK;
                        if(data_shift_count == 5'd8) sda_fsm_drive <= 1;
                        else sda_fsm_drive <= 0;
                    end
                    else begin
                        state <= ST_READ_DATA;
                    end
                end

                ST_READ_ACK: begin
                    // sda_fsm_drive <= 1;
                    if (!scl_drive) begin
                         if(SDA_bus) begin
                             state <= ST_STOP;
                         end
                         else begin
                            if(data_shift_count <= 5'd8) state <= ST_READ_DATA;
                            else begin
                                sda_fsm_drive <= 0;
                                state <= ST_STOP;
                                rdata <= rdata_sub_reg;
                                scl_en <= 1;
                            end
                            data_shift_count <= data_shift_count +1'b1;
                         end
                    end
                    else state <= ST_READ_ACK;

                end
                    
                ST_STOP:begin
                    sda_fsm_drive <= 1;
                    if(!scl_drive) begin
                        sda_fsm_drive <= 0;
                        state <= ST_IDLE;
                        scl_en <= 0;
                        write_update <= 0;
                    end 
                    else begin 
                        scl_en <= 0;
                    end
                    
                end    
                

                default: ;
            endcase
        end
    end


    
endmodule

tb/tb.v
// `timescale 1ns/1ns

module tb;
    `include "../tb/i2c_task.v"
    // Signals
    reg clk_i2c, clk;
    reg sda_drive;   // master điều khiển SDA
    wire SDA_bus;        // SDA line (pull-up)
    // Pull-up giả lập bus
    pullup(SDA_bus);
    
    wire SCL_bus;
    pullup(SCL_bus);
    reg int_sig;
    reg rst;
    
    integer error;
    localparam 
        I2C_PCF8575_FIST_4B_SLAVE_ADDR = 4'b0100,
        I2C_PCF8575_SET_3B = 3'b000,
        I2C_PCF8575_SLAVE_ADDR = {I2C_PCF8575_FIST_4B_SLAVE_ADDR,I2C_PCF8575_SET_3B};
    // DUT instance


    wire rst_n;
    assign rst_n = ~rst;
    reg [2:0] addr;
    reg [15:0] wdata;
    wire [15:0]  rdata;

    pcf8575 u_pcf8575 (
        .clk        (clk_i2c),
        .rst_n      (rst_n),

        .addr       (addr),
        .wdata      (wdata),
        .rdata      (rdata),

        .SDA_bus    (SDA_bus),
        .SCL_bus    (SCL_bus),
        .int_sig    (int_sig)
    );


    // Dump waveform ra file VCD
    initial begin
    `ifdef WAVE
        $display("=== DUMP NORMAL VCD ===");
        $dumpfile("dump.vcd");
        $dumpvars(0,tb.u_pcf8575);
    `elsif DEC
        $display("=== DUMP DEC VCD ===");
        $dumpfile("dump_dec.vcd");
        $dumpvars(0,
            tb.SDA_bus,
            tb.SCL_bus
        );
    `endif
    end

    // Kết nối SDA: master có thể drive low hoặc nhả ra
    assign SDA_bus = (sda_drive) ? 1'b0 :  1'bz;

    // Clock 100 MHz
    initial begin
        clk_i2c = 0;
        forever #100 clk_i2c = ~clk_i2c;  // 100 MHz
    end

    // Test sequence
    initial begin
        // Initialize
        rst = 1;
        addr = 0;
        int_sig = 0;
        sda_drive = 0 ;
        wdata = 0;
        #2;
        rst = 0;
        #10;

        $display("run test");
        wdata = 16'hf55f;
        $display("Set wdata = 16'h%h", wdata);
        #10;
        pcf8575_slave_handle_write();
        #120;

        int_sig = 1;
        pcf8575_slave_handle_read(16'hffff);
        int_sig = 0;
        $display("Read rdata = 16'h%h", rdata);
        #120;
        $finish;
    end

    initial begin
        #1000000;
        $finish;
    end

endmodule

sim/dump.vcd
$date
	Fri Jan 16 18:40:27 2026
$end
$version
	Icarus Verilog
$end
$timescale
	1s
$end
$scope module tb $end
$scope module u_pcf8575 $end
$var wire 1 ! SCL_bus $end
$var wire 1 " SDA_bus $end
$var wire 3 # addr [2:0] $end
$var wire 1 $ clk $end
$var wire 1 % int_sig $end
$var wire 1 & rst_n $end
$var wire 16 ' wdata [15:0] $end
$var parameter 4 ( I2C_PCF8575_FIST_4B_SLAVE_ADDR $end
$var parameter 4 ) ST_ADDR_ACK $end
$var parameter 4 * ST_IDLE $end
$var parameter 4 + ST_READ_ACK $end
$var parameter 4 , ST_READ_DATA $end
$var parameter 4 - ST_SLAVE_ADDR $end
$var parameter 4 . ST_START $end
$var parameter 4 / ST_STOP $end
$var parameter 4 0 ST_WRITE_ACK $end
$var parameter 4 1 ST_WRITE_DATA $end
$var reg 5 2 data_shift_count [4:0] $end
$var reg 16 3 rdata [15:0] $end
$var reg 16 4 rdata_sub_reg [15:0] $end
$var reg 1 5 scl_drive $end
$var reg 1 6 scl_en $end
$var reg 1 7 sda_fsm_drive $end
$var reg 4 8 state [3:0] $end
$var reg 16 9 wdata_sub_reg [15:0] $end
$var reg 1 : write_update $end
$upscope $end
$upscope $end
$enddefinitions $end
$comment Show the parameter values. $end
$dumpall
b101 1
b110 0
b1001 /
b1 .
b10 -
b111 ,
b1000 +
b0 *
b100 )
b100 (
$end
#0
$dumpvars
0:
b0 9
b0 8
07
06
05
b0 4
b0 3
b0 2
b0 '
0&
0%
0$
b0 #
1"
1!
$end
#2
1&
#12
b1111010101011111 '
#100
1$
#200
b1 8
1:
0$
#300
1$
#400
0"
b10 8
16
17
0$
#500
0!
15
1$
#600
17
0$
#700
1!
05
1$
#800
b1 2
17
0$
#900
0!
15
1$
#1000
1"
07
0$
#1100
1!
05
1$
#1200
b10 2
0$
#1300
0!
15
1$
#1400
0"
17
0$
#1500
1!
05
1$
#1600
b11 2
17
0$
#1700
0!
15
1$
#1800
17
0$
#1900
1!
05
1$
#2000
b100 2
17
0$
#2100
0!
15
1$
#2200
17
0$
#2300
1!
05
1$
#2400
b101 2
17
0$
#2500
0!
15
1$
#2600
17
0$
#2700
1!
05
1$
#2800
b110 2
17
0$
#2900
0!
15
1$
#3000
17
0$
#3100
1!
05
1$
#3200
b111 2
17
0$
#3300
0!
15
1$
#3400
17
0$
#3500
1!
05
1$
#3600
b1000 2
17
0$
#3700
0!
15
1$
#3800
b100 8
07
0$
#3900
1!
05
1$
#4000
b0 2
b1111010101011111 9
b101 8
0$
#4100
1"
0!
15
1$
#4200
b110 8
0$
#4300
1!
05
1$
#4400
b1001 8
0$
#4500
0!
15
1$
#4600
0"
06
17
0$
#4700
1!
05
1$
#4800
1"
0:
b0 8
07
0$
#4900
1$
#5000
b1 8
0$
#5100
1$
#5200
0"
b10 8
16
17
0$
#5300
0!
15
1$
#5400
17
0$
#5500
1!
05
1$
#5600
b1 2
17
0$
#5700
0!
15
1$
#5800
1"
07
0$
#5900
1!
05
1$
#6000
b10 2
0$
#6100
0!
15
1$
#6200
0"
17
0$
#6300
1!
05
1$
#6400
b11 2
17
0$
#6500
0!
15
1$
#6600
17
0$
#6700
1!
05
1$
#6800
b100 2
17
0$
#6900
0!
15
1$
#7000
17
0$
#7100
1!
05
1$
#7200
b101 2
17
0$
#7300
0!
15
1$
#7400
17
0$
#7500
1!
05
1$
#7600
b110 2
17
0$
#7700
0!
15
1$
#7800
17
0$
#7900
1!
05
1$
#8000
b111 2
17
0$
#8100
0!
15
1$
#8200
1"
07
0$
#8300
1!
05
1$
#8400
b1000 2
0$
#8500
0!
15
1$
#8600
b100 8
0$
#8700
1!
05
1$
#8800
b1001 8
0$
#8900
0!
15
1$
#9000
0"
06
17
0$
#9100
1!
05
1$
#9200
1"
b0 8
07
0$
#9300
1$
#9400
b1 8
b0 2
0$
#9500
1$
#9600
0"
b10 8
16
17
0$
#9700
0!
15
1$
#9800
17
0$
#9900
1!
05
1$
#10000
b1 2
17
0$
#10100
0!
15
1$
#10200
1"
07
0$
#10300
1!
05
1$
#10400
b10 2
0$
#10500
0!
15
1$
#10600
0"
17
0$
#10700
1!
05
1$
#10800
b11 2
17
0$
#10900
0!
15
1$
#11000
17
0$
#11100
1!
05
1$
#11200
b100 2
17
0$
#11300
0!
15
1$
#11400
17
0$
#11500
1!
05
1$
#11600
b101 2
17
0$
#11700
0!
15
1$
#11800
17
0$
#11900
1!
05
1$
#12000
b110 2
17
0$
#12100
0!
15
1$
#12200
17
0$
#12300
1!
05
1$
#12400
b111 2
17
0$
#12500
0!
15
1$
#12600
1"
07
0$
#12700
1!
05
1$
#12800
b1000 2
0$
#12900
0!
15
1$
#13000
b100 8
0$
#13100
1!
05
1$
#13200
b1001 8
0$
#13300
0!
15
1$
#13400
0"
06
17
0$
#13500
1!
05
1$
#13600
1"
b0 8
07
0$
#13700
1$
#13720
1%
#13800
b0 2
0$
