tb/i2c_task.v
// ==== SLAVE HANDLE WRITE (Master writes to PCF8575) ====
task pcf8575_slave_handle_write();
    integer rdata;
    begin
        $display("=====pcf8575_slave_handle_write=====");
        slave_wait_start();

        slave_receive_byte(rdata); // address + W

        if (rdata == {I2C_PCF8575_SLAVE_ADDR, 1'b0}) begin
            // Correct address + WRITE
            $display("[PCF8575] Address matched: 7'h%h, WRITE operation",rdata[7:1]);
            slave_send_ack(1);

            slave_receive_byte(rdata); // MSB
            slave_send_ack(1);

            slave_receive_byte(rdata); // LSB
            slave_send_ack(0);
        end
        else if (rdata[7:1] == I2C_PCF8575_SLAVE_ADDR) begin
            // Address correct but R/W bit wrong
            $display("[PCF8575] Address matched but R/W bit incorrect (Expected WRITE)");
            slave_send_ack(0); // optional NACK
        end
        else begin
            // Address incorrect
            $display("[PCF8575] Address mismatch (Wrong slave address)");
            slave_send_ack(0); // optional NACK
        end


        slave_wait_stop();
    end
endtask


// ==== SLAVE HANDLE READ (Master reads from PCF8575) ====
task pcf8575_slave_handle_read(
        input [15:0] data
    );
    integer rdata;
    integer master_ack;
    begin
        $display("=====pcf8575_slave_handle_read=====");
        master_ack = 0;
        slave_wait_start();

        slave_receive_byte(rdata); // address + R
        
        if (rdata == {I2C_PCF8575_SLAVE_ADDR, 1'b1}) begin
            // Correct address + READ
            $display("[PCF8575] Address matched: 7'h%h, READ operation",rdata[7:1]);
            slave_send_ack(1);

            slave_transmit_byte(data[15:8]); // MSB
            slave_check_master_ack(master_ack);

            if (master_ack) begin
                slave_transmit_byte(data[7:0]); // LSB
                slave_check_master_ack(master_ack);
            end
        end
        else if (rdata[7:1] == I2C_PCF8575_SLAVE_ADDR) begin
            // Address correct but R/W bit wrong
            $display("[PCF8575] Address matched but R/W bit incorrect (Expected READ)");
            slave_send_ack(0); // optional: NACK wrong direction
        end
        else begin
            // Address incorrect
            $display("[PCF8575] Address mismatch (Wrong slave address)");
            slave_send_ack(0); // optional
        end


        slave_wait_stop();
    end
endtask


// ==== WAIT START CONDITION ====
task slave_wait_start();
    reg detect;
    begin
        $display("[%0t] [PCF8575] Waiting for START condition", $time);
        detect = 0;
        while (!detect) begin
            @(negedge tb.SDA_bus);
            if (tb.SCL_bus === 1'b1) begin
                $display("[%0t] [PCF8575] START detected", $time);
                detect = 1;
            end
        end
    end
endtask


// ==== WAIT STOP CONDITION ====
task slave_wait_stop();
    reg detect;
    begin
        $display("[%0t] [PCF8575] Waiting for STOP condition", $time);
        detect = 0;
        while (!detect) begin
            @(posedge tb.SDA_bus);
            if (tb.SCL_bus === 1'b1) begin
                $display("[%0t] [PCF8575] STOP detected", $time);
                detect = 1;
            end
        end
    end
endtask


// ==== SLAVE RECEIVE BYTE FROM MASTER ====
task slave_receive_byte(output [7:0] data);
    integer i;
    begin
        tb.sda_drive = 0; // release SDA
        for (i = 8; i > 0; i = i - 1) begin
            @(posedge tb.SCL_bus)
                data[i-1] = tb.SDA_bus;
        end
        $display("[%0t] [PCF8575] Received byte: 0x%02h", $time, data);
    end
endtask


// ==== SLAVE TRANSMIT BYTE TO MASTER ====
task slave_transmit_byte(input [7:0] data);
    integer i;
    begin
        $display("[%0t] [PCF8575] Transmitting byte: 0x%02h", $time, data);
        for (i = 8; i > 0; i = i - 1) begin
            @(negedge tb.SCL_bus)
                tb.sda_drive = ~data[i-1];
        end
    end
endtask


// ==== SLAVE SEND ACK/NACK ====
task slave_send_ack(input ack);
    begin
        @(negedge tb.SCL_bus) tb.sda_drive = ack;
        if (ack)
            $display("[%0t] [PCF8575] Send ACK", $time);
        else
            $display("[%0t] [PCF8575] Send NACK", $time);
        @(negedge tb.SCL_bus) tb.sda_drive = 0; // release SDA
    end
endtask


// ==== SLAVE CHECK MASTER ACK ====
task slave_check_master_ack(output ack);
    begin
        @(negedge tb.SCL_bus) tb.sda_drive = 0;
        @(posedge tb.SCL_bus) ack = tb.sda_drive;

        if (ack)
            $display("[%0t] [PCF8575] Master ACK received", $time);
        else
            $display("[%0t] [PCF8575] Master NACK received", $time);
    end
endtask

src/pcf8575_old.v
module pcf8575 (
    input wire clk, rst_n,

    input wire [2:0] addr,
    input wire wr_en, rd_en,
    input wire [15:0] wdata,
    output wire [15:0] rdata,

    inout wire SDA_bus,
    inout wire SCL_bus,
    input wire int_sig
);

    localparam I2C_PCF8575_FIST_4B_SLAVE_ADDR = 4'b0100;

    reg scl_en, scl_drive;
    assign SCL_bus = (scl_drive)? 1'b0: 1'bz;

    always @(posedge clk , negedge rst_n) begin
        if(!rst_n) scl_drive <= 1'b0;
        else if (scl_en) scl_drive <= ~scl_drive;
        else scl_drive <= 1'b0;
    end

    
    
    reg [7:0] data_shift_out;
    reg sda_shift_out_drive, sda_fsm_drive;
    assign SDA_bus = (sda_shift_out_drive || sda_fsm_drive)?  1'b0 : 1'bz;

    reg [2:0] data_shift_count;

    reg write_shift_start, write_shift_busy;
    reg shift_state;
    localparam  ST_SHIFT_IDLE  = 1'b0,
                ST_SHIFT_START = 1'b1;

    //write
    always @(negedge clk , negedge rst_n ) begin
        if(!rst_n) begin
            sda_shift_out_drive <= 1'b0;
            data_shift_count <= 0;
            data_shift_out <= 0;
            write_shift_busy <= 0;
            shift_state <= ST_SHIFT_IDLE;
        end
        else begin
            case (shift_state)
                ST_SHIFT_IDLE :  begin
                    data_shift_count <= 0;
                    sda_shift_out_drive <= 0;
                    if(write_shift_start) begin
                        shift_state <= ST_SHIFT_START;
                        write_shift_busy <= 1'b1;
                    end
                    else begin
                        write_shift_busy <= 1'b0;
                    end 
                end

                ST_SHIFT_START :  begin
                    sda_shift_out_drive <= ~data_shift_out[3'd7-data_shift_count];
                    if (!scl_drive) begin
                        data_shift_count <= data_shift_count + 1'b1;
                        if(data_shift_count == 3'd7) begin
                            shift_state <= ST_SHIFT_IDLE;
                            data_shift_count <= 0;
                            write_shift_busy <= 1'b0;
                            sda_shift_out_drive <= 0;
                        end
                    end 
                    else  data_shift_count <= data_shift_count;

                    
                end

                default: ;
            endcase
        

        end
    end
        
    reg [3:0] state, next_state;
    reg data_byte_count;

    reg[15:0] wdata_sub_reg, rdata_sub_reg;
    wire write_update;
    assign write_update = 1'b1;
// assign write_update = (wdata_sub_reg != rdata_sub_reg));

    localparam
        ST_IDLE        = 4'd0,
        ST_START       = 4'd1,
        ST_SLAVE_ADDR  = 4'd2,
        ST_HALT = 4'd3,
        ST_ADDR_ACK    = 4'd4,
        ST_WRITE_DATA  = 4'd5,
        ST_WRITE_ACK   = 4'd6,
        ST_READ_DATA   = 4'd7,
        ST_READ_ACK    = 4'd8,
        ST_STOP        = 4'd9;


    always @(posedge clk , negedge rst_n) begin
        if(!rst_n)begin
            state <= ST_IDLE;
            wdata_sub_reg <= 0;
            rdata_sub_reg <= 0;
            sda_fsm_drive <= 1'b0;
            write_shift_start <= 0;
            data_shift_count <= 0;
            data_byte_count <= 0;
            scl_en <= 0;
        end
        else begin
            case (state)
                ST_IDLE: begin
                    if(write_update || int_sig) begin
                        state <= ST_START;
                        
                        sda_fsm_drive <= 0;
                    end
                    else begin
                        state <= ST_IDLE;
                        sda_fsm_drive <= 0;
                    end
                end 

                ST_START: begin
                    sda_fsm_drive <= 1;
                    scl_en <= 1;
                    state <= ST_SLAVE_ADDR;
                    
                end

                ST_SLAVE_ADDR:begin
                    write_shift_start <= 1;
                    sda_fsm_drive <= 0;
                    if(!write_shift_busy) begin
                        // if(data_byte_count == 1) begin
                            
                            // data_byte_count <= 0;
                        // end
                        // else begin
                            // data_byte_count <= data_byte_count + 1'b1;
                            
                            state <= ST_ADDR_ACK;
                            if(write_update)   data_shift_out <= {I2C_PCF8575_FIST_4B_SLAVE_ADDR, addr, 1'b0};
                            else if(int_sig)   data_shift_out <= {I2C_PCF8575_FIST_4B_SLAVE_ADDR, addr, 1'b1};
                            else state <= ST_STOP;
                        // end
                    end
                    else begin
                        state <= ST_SLAVE_ADDR;
                        write_shift_start <= 0;
                        // write_shift_start <= 0;
                    end
                end

                ST_ADDR_ACK:begin
                    // if(SDA_bus) begin
                    //     state <= STOP;
                    // end
                    // else begin
                    if (scl_drive) begin
                        state <= ST_WRITE_DATA;
                    end
                        
                    // end
                end

                ST_WRITE_DATA:begin
                    write_shift_start <= 1;
                    if(!write_shift_busy ) begin
                        data_shift_out <= wdata[data_byte_count*8 +: 8];
                        // if (write_shift_start) 
                        state <= ST_WRITE_ACK;
                        // else state <= ST_WRITE_DATA;
                    end
                    else begin
                        state <= ST_WRITE_DATA;
                        write_shift_start <= 0;
                    end
                end

                ST_WRITE_ACK: begin
                    if (scl_drive) begin
                        // if(SDA_bus) begin
                        //     state <= ST_STOP;
                        // end
                        // else begin
                            if(data_byte_count == 1) begin
                                state <= ST_STOP;
                                data_byte_count <= 0;
                                write_shift_start <= 0;
                            end
                            else begin
                                state <= ST_WRITE_DATA;
                                data_byte_count <= data_byte_count + 1'b1;
                            end
                        // end
                    end
                end
                    
                ST_STOP:begin
                    if(!write_shift_busy) begin
                        sda_fsm_drive <= 1;
                        state <= ST_HALT;
                    end
                    else begin
                        sda_fsm_drive <= 0;
                    end
                    
                    // state <= ST_IDLE;
                end    

                ST_HALT: begin
                    state <= ST_HALT;
                    sda_fsm_drive <= 0;

                    wdata_sub_reg <= 0;
                    rdata_sub_reg <= 0;
                    sda_fsm_drive <= 1'b0;
                    write_shift_start <= 0;
                    data_shift_count <= 0;
                    data_byte_count <= 0;
                    scl_en <= 0;
                end 
                

                default: ;
            endcase
        end
    end


    
endmodule

tb/tb.v
// `timescale 1ns/1ns

module tb;
    `include "../tb/i2c_task.v"
    // Signals
    reg clk_i2c, clk;
    reg sda_drive;   // master điều khiển SDA
    wire SDA_bus;        // SDA line (pull-up)
    // Pull-up giả lập bus
    pullup(SDA_bus);
    
    wire SCL_bus;
    pullup(SCL_bus);
    reg int_sig;
    reg rst;
    
    integer error;
    localparam 
        I2C_PCF8575_FIST_4B_SLAVE_ADDR = 4'b0100,
        I2C_PCF8575_SET_3B = 3'b000,
        I2C_PCF8575_SLAVE_ADDR = {I2C_PCF8575_FIST_4B_SLAVE_ADDR,I2C_PCF8575_SET_3B};
    // DUT instance


    wire rst_n;
    assign rst_n = ~rst;
    reg [2:0] addr;
    reg [15:0] wdata;
    wire [15:0]  rdata;

    pcf8575 u_pcf8575 (
        .clk        (clk_i2c),
        .rst_n      (rst_n),

        .addr       (addr),
        .wdata      (wdata),
        .rdata      (rdata),

        .SDA_bus    (SDA_bus),
        .SCL_bus    (SCL_bus),
        .int_sig    (int_sig)
    );


    // Dump waveform ra file VCD
    initial begin
    `ifdef WAVE
        $display("=== DUMP NORMAL VCD ===");
        $dumpfile("dump.vcd");
        $dumpvars(0,tb.u_pcf8575);
    `elsif DEC
        $display("=== DUMP DEC VCD ===");
        $dumpfile("dump_dec.vcd");
        $dumpvars(0,
            tb.SDA_bus,
            tb.SCL_bus
        );
    `endif
    end

    // Kết nối SDA: master có thể drive low hoặc nhả ra
    assign SDA_bus = (sda_drive) ? 1'b0 :  1'bz;

    // Clock 100 MHz
    initial begin
        clk_i2c = 0;
        forever #100 clk_i2c = ~clk_i2c;  // 100 MHz
    end

    // Test sequence
    initial begin
        // Initialize
        rst = 1;
        addr = 0;
        int_sig = 0;
        sda_drive = 0 ;
        wdata = 0;
        #2;
        rst = 0;
        #10;

        $display("run test");
        wdata = 16'hf55f;
        $display("Set wdata = 16'h%h", wdata);
        #10;
        pcf8575_slave_handle_write();
        #120;

        int_sig = 1;
        pcf8575_slave_handle_read(16'hffff);
        int_sig = 0;
        $display("Read rdata = 16'h%h", rdata);
        #120;
        $finish;
    end

    initial begin
        #1000000;
        $finish;
    end

endmodule

sim/dump_dec.vcd
$date
	Fri Jan 16 18:53:41 2026
$end
$version
	Icarus Verilog
$end
$timescale
	1s
$end
$scope module tb $end
$var wire 1 ! SDA_bus $end
$upscope $end
$scope module tb $end
$var wire 1 " SCL_bus $end
$upscope $end
$enddefinitions $end
$comment Show the parameter values. $end
$dumpall
$end
#0
$dumpvars
1"
1!
$end
#400
0!
#500
0"
#700
1"
#900
0"
#1000
1!
#1100
1"
#1300
0"
#1400
0!
#1500
1"
#1700
0"
#1900
1"
#2100
0"
#2300
1"
#2500
0"
#2700
1"
#2900
0"
#3100
1"
#3300
0"
#3500
1"
#3700
0"
#3900
1"
#4100
1!
0"
#4200
0!
#4300
1"
#4500
0"
#4600
1!
#4700
1"
#4900
0"
#5000
0!
#5100
1"
#5300
0"
#5400
1!
#5500
1"
#5700
0"
#5900
1"
#6100
0"
#6300
1"
#6500
0"
#6700
1"
#6900
0"
#7100
1"
#7300
0!
0"
#7500
1"
#7700
1!
0"
#7900
1"
#8100
0"
#8300
1"
#8500
0"
#8700
1"
#8900
0"
#9100
1"
#9300
0"
#9400
0!
#9500
1"
#9700
0"
#9800
1!
#9900
1"
#10100
0"
#10200
0!
#10300
1"
#10500
0"
#10600
1!
#10700
1"
#10900
0"
#11100
1"
#11300
0"
#11400
0!
#11500
1"
#11600
1!
